openai_batch/__init__.py
openai_batch/_utils.py
openai_batch/batch.py
openai_batch/create_batch_input.py
openai_batch/create_input.py
openai_batch/example_prompts.py
openai_batch/providers.py
openai_batch/run.py
openai_batch-0.3.4.dist-info/licenses/LICENSE
tests/__init__.py
tests/test_basic.py
tests/test_create.py
tests/test_live.py
tests/test_run.py
tests/test_utils.py
tests/two_man_720.jpg
tests/resources/example.jpg
openai_batch-0.3.4.dist-info/METADATA
openai_batch-0.3.4.dist-info/WHEEL
openai_batch-0.3.4.dist-info/top_level.txt
openai_batch-0.3.4.dist-info/RECORD
