Metadata-Version: 2.4
Name: openai-batch
Version: 0.3.4
Summary: Make OpenAI batch easy to use.
Author: Parasail
License-Expression: Apache-2.0
Project-URL: homepage, https://github.com/parasail-ai/openai-batch
Project-URL: repository, https://github.com/parasail-ai/openai-batch
Keywords: openai,batch,chatgpt,gpt,llm,language model
Classifier: Development Status :: 4 - Beta
Classifier: Intended Audience :: Science/Research
Classifier: Intended Audience :: Developers
Classifier: Programming Language :: Python :: 3 :: Only
Classifier: Topic :: Software Development :: Libraries
Classifier: Topic :: Scientific/Engineering
Requires-Python: >=3.9
License-File: LICENSE
Requires-Dist: openai>=1.60
Provides-Extra: test
Requires-Dist: black; extra == "test"
Requires-Dist: pytest; extra == "test"
Requires-Dist: python-dotenv; extra == "test"
Requires-Dist: filetype; extra == "test"
Requires-Dist: pillow; extra == "test"
Dynamic: license-file
